autodatamind/__init__.py
autodatamind/agents/__init__.py
autodatamind/agents/data_agent.py
autodatamind/agents/dl_agent.py
autodatamind/agents/insight_agent.py
autodatamind/agents/ml_agent.py
autodatamind/agents/profile_agent.py
autodatamind/agents/viz_agent.py
autodatamind/core/__init__.py
autodatamind/core/cleaner.py
autodatamind/core/reader.py
autodatamind/core/utils.py
autodatamind/core/validator.py
autodatamind/models/__init__.py
autodatamind/models/auto_dl.py
autodatamind/models/auto_ml.py
autodatamind/outputs/__init__.py
autodatamind-0.1.1.dist-info/licenses/LICENSE
autodatamind-0.1.1.dist-info/METADATA
autodatamind-0.1.1.dist-info/WHEEL
autodatamind-0.1.1.dist-info/top_level.txt
autodatamind-0.1.1.dist-info/RECORD
