Metadata-Version: 2.4
Name: autodatamind
Version: 0.1.1
Summary: Zero-code automated data analysis, machine learning, and deep learning
Home-page: https://github.com/idrissbado/autodatamind
Author: Idriss Olivier Bado
Author-email: Idriss Olivier Bado <idrissbadoolivier@gmail.com>
License: MIT
Project-URL: Homepage, https://github.com/idrissbado/autodatamind
Project-URL: Documentation, https://github.com/idrissbado/autodatamind#readme
Project-URL: Repository, https://github.com/idrissbado/autodatamind
Project-URL: Bug Tracker, https://github.com/idrissbado/autodatamind/issues
Keywords: automated-ml,automl,deep-learning,machine-learning,data-analysis,zero-code
Classifier: Development Status :: 4 - Beta
Classifier: Intended Audience :: Developers
Classifier: Intended Audience :: Science/Research
Classifier: Intended Audience :: Education
Classifier: Topic :: Scientific/Engineering :: Artificial Intelligence
Classifier: License :: OSI Approved :: MIT License
Classifier: Programming Language :: Python :: 3
Classifier: Programming Language :: Python :: 3.8
Classifier: Programming Language :: Python :: 3.9
Classifier: Programming Language :: Python :: 3.10
Classifier: Programming Language :: Python :: 3.11
Requires-Python: >=3.8
License-File: LICENSE
Requires-Dist: pandas>=2.0.0
Requires-Dist: numpy>=1.24.0
Requires-Dist: scikit-learn>=1.3.0
Requires-Dist: torch>=2.0.0
Requires-Dist: matplotlib>=3.7.0
Requires-Dist: seaborn>=0.12.0
Requires-Dist: openpyxl>=3.1.0
Requires-Dist: pyarrow>=12.0.0
Requires-Dist: joblib>=1.3.0
Dynamic: author
Dynamic: home-page
Dynamic: license-file
Dynamic: requires-python
